socialgal-1.0.0a0.dist-info/METADATA
socialgal-1.0.0a0.dist-info/WHEEL
socialgal-1.0.0a0.dist-info/licenses/LICENSE
socialgal/__init__.py
socialgal/client/__init__.py
socialgal/client/client.py
socialgal/types/__init__.py
socialgal/types/post.py
socialgal/types/user.py
socialgal-1.0.0a0.dist-info/RECORD
