Metadata-Version: 2.1
Name: socialgal
Version: 1.0.0a0
Summary: An async API wrapper for SocialGal written in Python.
Author-Email: vcokltfre <vcokltfre@gmail.com>
License: MIT
Requires-Python: >=3.10
Requires-Dist: httpx>=0.25.0
